pysec_inspect/__init__.py
pysec_inspect/__main__.py
pysec_inspect/config.py
pysec_inspect-1.0.1.dist-info/licenses/LICENSE
pysec_inspect-1.0.1.dist-info/METADATA
pysec_inspect-1.0.1.dist-info/WHEEL
pysec_inspect-1.0.1.dist-info/entry_points.txt
pysec_inspect-1.0.1.dist-info/top_level.txt
pysec_inspect-1.0.1.dist-info/RECORD
