Metadata-Version: 2.4
Name: pysec-inspect
Version: 1.0.1
Summary: An automated tool for comprehensive security audit of Python applications with performance and code quality analysis functions
Author-email: ursaloper <asejerman56@gmail.com>
License: MIT
Project-URL: Homepage, https://github.com/ursaloper/pysec_inspect
Project-URL: Bug Tracker, https://github.com/ursaloper/pysec_inspect/issues
Keywords: security,performance,code-quality,static-analysis,python
Classifier: Programming Language :: Python :: 3
Classifier: Programming Language :: Python :: 3.9
Classifier: Programming Language :: Python :: 3.10
Classifier: Programming Language :: Python :: 3.11
Classifier: License :: OSI Approved :: MIT License
Classifier: Operating System :: OS Independent
Classifier: Topic :: Security
Classifier: Topic :: Software Development :: Quality Assurance
Requires-Python: >=3.9
License-File: LICENSE
Requires-Dist: pyyaml>=6.0
Requires-Dist: rich>=10.0.0
Requires-Dist: tqdm>=4.65.0
Requires-Dist: markdown>=3.4.0
Requires-Dist: pygments>=2.13.0
Provides-Extra: ai
Requires-Dist: openai>=1.0.0; extra == "ai"
Requires-Dist: anthropic>=0.5.0; extra == "ai"
Provides-Extra: dev
Requires-Dist: pytest>=7.0.0; extra == "dev"
Requires-Dist: black>=22.0.0; extra == "dev"
Requires-Dist: isort>=5.0.0; extra == "dev"
Requires-Dist: mypy>=0.9.0; extra == "dev"
Dynamic: license-file
